plyppy/__init__.py
plyppy/__main__.py
plyppy/assets/bullet.png
plyppy/assets/entry.png
plyppy/assets/lock.png
plyppy-0.0.1.dist-info/LICENSE
plyppy-0.0.1.dist-info/METADATA
plyppy-0.0.1.dist-info/WHEEL
plyppy-0.0.1.dist-info/entry_points.txt
plyppy-0.0.1.dist-info/top_level.txt
plyppy-0.0.1.dist-info/RECORD
