Metadata-Version: 2.1
Name: plyppy
Version: 0.0.1
Summary: Plyppy: A Plymouth Boot Splash Generator
Author-email: Sarthak Shah <shahsarthakw@gmail.com>
License: GPL-3.0-or-later
Project-URL: Homepage, https://github.com/cel7t/plyppy
Project-URL: Issues, https://github.com/cel7t/plyppy/issues
Requires-Python: >=3.8
License-File: LICENSE
Requires-Dist: pillow
Requires-Dist: opencv-python
Requires-Dist: rembg
Requires-Dist: rich
Requires-Dist: importlib
